cube3d/__init__.py
cube3d/base.py
cube3d/input.py
cube3d-0.0.1.dist-info/LICENSE
cube3d-0.0.1.dist-info/METADATA
cube3d-0.0.1.dist-info/WHEEL
cube3d-0.0.1.dist-info/top_level.txt
cube3d-0.0.1.dist-info/RECORD
