Metadata-Version: 2.1
Name: cube3d
Version: 0.0.1
Summary: 3-Dimention Rubic cube activities
Home-page: https://github.com/alias1978/cube3d
Author: ALIASGAR - ALI
Author-email: aholo2000@gmail.com
License: UNKNOWN
Platform: UNKNOWN
Classifier: Programming Language :: Python :: 3
Classifier: License :: OSI Approved :: MIT License
Classifier: Operating System :: OS Independent
Requires-Python: >=3.7
License-File: LICENSE
Requires-Dist: pandas
Requires-Dist: xlrd
Requires-Dist: numpy
